budgetwise/__init__.py
budgetwise/calculate_budget.py
budgetwise-0.1.dist-info/METADATA
budgetwise-0.1.dist-info/WHEEL
budgetwise-0.1.dist-info/top_level.txt
budgetwise-0.1.dist-info/RECORD
