Metadata-Version: 2.1
Name: budgetwise
Version: 0.1
Summary: Easily calculate budgets for your company
Home-page: https://github.com/kaarelr/budgetwise
Author: Cloudberry
Author-email: kaarel.reinvars@gmail.com
License: MIT
Platform: UNKNOWN
